Xdisplay/__init__.py
Xdisplay/xdisplay.py
xdisplay-0.0.3.dist-info/METADATA
xdisplay-0.0.3.dist-info/WHEEL
xdisplay-0.0.3.dist-info/RECORD
